rudydesplan_de_toolkit/__init__.py
rudydesplan_de_toolkit/main.py
rudydesplan_de_toolkit/vm.py
rudydesplan_de_toolkit-0.1.0.dist-info/METADATA
rudydesplan_de_toolkit-0.1.0.dist-info/WHEEL
rudydesplan_de_toolkit-0.1.0.dist-info/entry_points.txt
rudydesplan_de_toolkit-0.1.0.dist-info/RECORD
