Metadata-Version: 2.1
Name: rudydesplan-de-toolkit
Version: 0.1.0
Summary: 
Author: rudy desplan
Author-email: desrudy@hotmail.com
Requires-Python: >=3.12,<4.0
Classifier: Programming Language :: Python :: 3
Classifier: Programming Language :: Python :: 3.12
Requires-Dist: click (>=8.1.7,<9.0.0)
